four_to_one_mux/multiplexer_2_1.v
module multiplexer_2_1(
	input a,
	input b,
	input s,
	output y
);
	assign y = (s)?b:a;
endmodule

four_to_one_mux/four_to_one_mux.v
module four_to_one_mux(
	input [3:0] i,
	input [1:0] s,
	output y
);
	wire s1,s2;
	
	multiplexer_2_1 inst1(.a(i[0]), .b(i[1]), .s(s[1]), .y(s1));
	multiplexer_2_1 inst2(.a(i[2]), .b(i[3]), .s(s[1]), .y(s2));
	multiplexer_2_1 inst3(.a(s1), .b(s2), .s(s[0]), .y(y));
endmodule

four_to_one_mux/four_to_one_mux_tb.v
`timescale 1ns/100ps;
module four_to_one_mux_tb;

	reg [3:0] i;
	reg [1:0] s;
	wire y;
	
	four_to_one_mux dut(
		.i(i),
		.s(s),
		.y(y)
	);

	initial begin
	$dumpfile("test_four_to_one_mux.vcd");
	$dumpvars(0,four_to_one_mux_tb);
	i = 4'b0001; s = 2'b00; #10;  // Expect y = i[0]
        i = 4'b0010; s = 2'b00; #10;  // Expect y = i[0]
        i = 4'b0010; s = 2'b01; #10;  // Expect y = i[1]
        i = 4'b1000; s = 2'b10; #10;  // Expect y = i[2]
        i = 4'b1000; s = 2'b11; #10;  // Expect y = i[3]
        
        // Try more combinations
        i = 4'b1111; s = 2'b00; #10;
        i = 4'b1010; s = 2'b01; #10;
        i = 4'b1100; s = 2'b10; #10;
        i = 4'b0110; s = 2'b11; #10;
	$finish;
	end
endmodule

four_to_one_mux/test_four_to_one_mux.vcd
$date
	Wed Jul  2 14:13:02 2025
$end
$version
	Icarus Verilog
$end
$timescale
	100ps
$end
$scope module four_to_one_mux_tb $end
$var wire 1 ! y $end
$var reg 4 " i [3:0] $end
$var reg 2 # s [1:0] $end
$scope module dut $end
$var wire 4 $ i [3:0] $end
$var wire 2 % s [1:0] $end
$var wire 1 ! y $end
$var wire 1 & s2 $end
$var wire 1 ' s1 $end
$scope module inst1 $end
$var wire 1 ( a $end
$var wire 1 ) b $end
$var wire 1 * s $end
$var wire 1 ' y $end
$upscope $end
$scope module inst2 $end
$var wire 1 + a $end
$var wire 1 , b $end
$var wire 1 - s $end
$var wire 1 & y $end
$upscope $end
$scope module inst3 $end
$var wire 1 ' a $end
$var wire 1 & b $end
$var wire 1 . s $end
$var wire 1 ! y $end
$upscope $end
$upscope $end
$upscope $end
$enddefinitions $end
$comment Show the parameter values. $end
$dumpall
$end
#0
$dumpvars
0.
0-
0,
0+
0*
0)
1(
1'
0&
b0 %
b1 $
b0 #
b1 "
1!
$end
#100
0!
0'
0(
1)
b10 "
b10 $
#200
1.
b1 #
b1 %
#300
1&
1*
1-
0.
0)
1,
b10 #
b10 %
b1000 "
b1000 $
#400
1!
1.
b11 #
b11 %
#500
1'
0*
0-
0.
1(
1)
1+
b0 #
b0 %
b1111 "
b1111 $
#600
0!
0'
0&
1.
0(
0+
b1 #
b1 %
b1010 "
b1010 $
#700
1&
1*
1-
0.
0)
1+
b10 #
b10 %
b1100 "
b1100 $
#800
1'
0&
1.
1)
0,
b11 #
b11 %
b110 "
b110 $
