serial_adder/serial_adder.v
module serial_adder (
    input clk,
    input rst,
    input a,
    input b,
    output reg sum_bit,
    output reg [3:0] result,
    output reg done
);
    reg carry;
    reg [1:0] count;  // For 4-bit numbers, count 0 to 3

    always @(posedge clk or posedge rst) begin
        if (rst) begin
            carry <= 0;
            count <= 0;
            result <= 0;
            done <= 0;
        end else begin
            if (!done) begin
                {carry, sum_bit} <= a + b + carry;
                result[count] <= sum_bit;
                count <= count + 1;
                if (count == 3)
                    done <= 1;
            end
        end
    end
endmodule

serial_adder/testbench.v
`timescale 1ns/1ps

module tb_serial_adder;
    reg clk, rst;
    reg [3:0] a_in, b_in;
    wire [3:0] result;
    wire done;
    wire sum_bit;

    reg a_bit, b_bit;
    reg [3:0] a_shift, b_shift;

    integer i;

    serial_adder uut (
        .clk(clk),
        .rst(rst),
        .a(a_bit),
        .b(b_bit),
        .sum_bit(sum_bit),
        .result(result),
        .done(done)
    );

    always #5 clk = ~clk;

    initial begin
        $dumpfile("serial_adder.vcd");
        $dumpvars(0, tb_serial_adder);

        clk = 0;
        rst = 1;
        a_in = 4'b1011; // 11
        b_in = 4'b0101; // 5
        a_shift = a_in;
        b_shift = b_in;

        #10 rst = 0;

        for (i = 0; i < 4; i = i + 1) begin
            a_bit = a_shift[0];
            b_bit = b_shift[0];
            a_shift = a_shift >> 1;
            b_shift = b_shift >> 1;
            #10;
        end

        #20;
        $display("Sum = %b", result);  // Expected: 0000_0000 + 0000_0000 = result[3:0]
        $finish;
    end
endmodule

serial_adder/serial_adder.vcd
$date
	Wed Jul  9 16:00:48 2025
$end
$version
	Icarus Verilog
$end
$timescale
	1ps
$end
$scope module tb_serial_adder $end
$var wire 1 ! sum_bit $end
$var wire 4 " result [3:0] $end
$var wire 1 # done $end
$var reg 1 $ a_bit $end
$var reg 4 % a_in [3:0] $end
$var reg 4 & a_shift [3:0] $end
$var reg 1 ' b_bit $end
$var reg 4 ( b_in [3:0] $end
$var reg 4 ) b_shift [3:0] $end
$var reg 1 * clk $end
$var reg 1 + rst $end
$var integer 32 , i [31:0] $end
$scope module uut $end
$var wire 1 $ a $end
$var wire 1 ' b $end
$var wire 1 * clk $end
$var wire 1 + rst $end
$var reg 1 - carry $end
$var reg 2 . count [1:0] $end
$var reg 1 # done $end
$var reg 4 / result [3:0] $end
$var reg 1 ! sum_bit $end
$upscope $end
$upscope $end
$enddefinitions $end
$comment Show the parameter values. $end
$dumpall
$end
#0
$dumpvars
b0 /
b0 .
0-
bx ,
1+
0*
b101 )
b101 (
x'
b1011 &
b1011 %
x$
0#
b0 "
x!
$end
#5000
1*
#10000
0*
b10 )
b101 &
1'
1$
b0 ,
0+
#15000
b1 .
b0x "
b0x /
1-
0!
1*
#20000
0*
b1 )
b10 &
0'
b1 ,
#25000
b10 .
1*
#30000
0*
b0 )
b1 &
1'
0$
b10 ,
#35000
b11 .
1*
#40000
0*
b0 &
0'
1$
b11 ,
#45000
1#
b0 .
1*
#50000
0*
b100 ,
